macos_junk_cleaner/__init__.py
macos_junk_cleaner/cleaner.py
macos_junk_cleaner/main.py
macos_junk_cleaner/scanner.py
macos_junk_cleaner-1.0.0.dist-info/licenses/LICENSE
macos_junk_cleaner-1.0.0.dist-info/METADATA
macos_junk_cleaner-1.0.0.dist-info/WHEEL
macos_junk_cleaner-1.0.0.dist-info/entry_points.txt
macos_junk_cleaner-1.0.0.dist-info/top_level.txt
macos_junk_cleaner-1.0.0.dist-info/RECORD
