Metadata-Version: 2.4
Name: macos-junk-cleaner
Version: 1.0.0
Summary: A utility to list and clear junk files created by macOS indexation.
Author-email: João Caetano <joaomartinscaetano@proton.me>
License-Expression: MIT
Project-URL: Homepage, https://github.com/JCaet/mac-os-junk-cleaner
Project-URL: Repository, https://github.com/JCaet/mac-os-junk-cleaner
Project-URL: Issues, https://github.com/JCaet/mac-os-junk-cleaner/issues
Project-URL: Changelog, https://github.com/JCaet/mac-os-junk-cleaner/blob/main/CHANGELOG.md
Keywords: macos,cleanup,junk-files,ds_store,cli
Classifier: Development Status :: 4 - Beta
Classifier: Environment :: Console
Classifier: Intended Audience :: End Users/Desktop
Classifier: Operating System :: MacOS
Classifier: Programming Language :: Python :: 3
Classifier: Programming Language :: Python :: 3.9
Classifier: Programming Language :: Python :: 3.10
Classifier: Programming Language :: Python :: 3.11
Classifier: Programming Language :: Python :: 3.12
Classifier: Topic :: System :: Systems Administration
Classifier: Topic :: Utilities
Requires-Python: >=3.9
License-File: LICENSE
Requires-Dist: click>=8.0.0
Requires-Dist: rich>=12.0.0
Dynamic: license-file
